hightech_amazeing/__init__.py
hightech_amazeing/api_client.py
hightech_amazeing/configuration.py
hightech_amazeing/rest.py
hightech_amazeing/api/__init__.py
hightech_amazeing/api/maze_api.py
hightech_amazeing/api/mazes_api.py
hightech_amazeing/api/player_api.py
hightech_amazeing/models/__init__.py
hightech_amazeing/models/maze_info.py
hightech_amazeing/models/move_action.py
hightech_amazeing/models/player_info.py
hightech_amazeing/models/possible_actions_and_current_score.py
test/__init__.py
test/test_maze_api.py
test/test_maze_info.py
test/test_mazes_api.py
test/test_move_action.py
test/test_player_api.py
test/test_player_info.py
test/test_possible_actions_and_current_score.py
hightech_amazeing-1.0.7.dist-info/LICENSE
hightech_amazeing-1.0.7.dist-info/METADATA
hightech_amazeing-1.0.7.dist-info/WHEEL
hightech_amazeing-1.0.7.dist-info/top_level.txt
hightech_amazeing-1.0.7.dist-info/RECORD
