Metadata-Version: 2.1
Name: hightech-amazeing
Version: 1.0.7
Summary: Hightech A-maze-ing API
Home-page: https://maze.hightechict.nl
Author: HightechICT
Author-email: subhi.hamidi@hightechict.nl
License: UNKNOWN
Keywords: Swagger,A-maze-ing API
Platform: UNKNOWN
Classifier: Programming Language :: Python :: 3
Classifier: License :: OSI Approved :: MIT License
Classifier: Operating System :: OS Independent
License-File: LICENSE
Requires-Dist: certifi (>=2017.4.17)
Requires-Dist: python-dateutil (>=2.1)
Requires-Dist: six (>=1.10)
Requires-Dist: urllib3 (>=1.23)
